phillydb/__init__.py
phillydb/__version__.py
phillydb/additional_links.py
phillydb/carto_tables.py
phillydb/exceptions.py
phillydb/labelled_fields.py
phillydb/owner_search_queries.py
phillydb/search_queries.py
phillydb/tables.py
phillydb/testing_utils.py
phillydb/utils.py
phillydb-0.2.6.dist-info/LICENSE
phillydb-0.2.6.dist-info/METADATA
phillydb-0.2.6.dist-info/WHEEL
phillydb-0.2.6.dist-info/entry_points.txt
phillydb-0.2.6.dist-info/top_level.txt
phillydb-0.2.6.dist-info/RECORD
