Metadata-Version: 2.1
Name: phillydb
Version: 0.2.6
Summary: A python client for accessing open property data for Philadelphia
Home-page: UNKNOWN
License: UNKNOWN
Platform: UNKNOWN
License-File: LICENSE
Requires-Dist: pandas
Requires-Dist: requests
Requires-Dist: passyunk
Requires-Dist: usaddress-scourgify
Requires-Dist: fuzzywuzzy
